dev_cmd/__init__.py
dev_cmd/__main__.py
dev_cmd/brace_substitution.py
dev_cmd/color.py
dev_cmd/console.py
dev_cmd/errors.py
dev_cmd/expansion.py
dev_cmd/invoke.py
dev_cmd/model.py
dev_cmd/parse.py
dev_cmd/placeholder.py
dev_cmd/project.py
dev_cmd/run.py
dev_cmd/venv.py
dev_cmd-0.32.4.dist-info/METADATA
dev_cmd-0.32.4.dist-info/WHEEL
dev_cmd-0.32.4.dist-info/entry_points.txt
dev_cmd-0.32.4.dist-info/top_level.txt
dev_cmd-0.32.4.dist-info/licenses/LICENSE
dev_cmd-0.32.4.dist-info/pylock/pylock.toml
dev_cmd-0.32.4.dist-info/RECORD
