Metadata-Version: 2.4
Name: dev-cmd
Version: 0.32.4
Summary: A simple development command runner for Python projects.
Author-email: John Sirois <john.sirois@gmail.com>
License-Expression: Apache-2.0
Project-URL: Repository, https://github.com/jsirois/dev-cmd
Project-URL: Bug Tracker, https://github.com/jsirois/dev-cmd/issues
Project-URL: Changelog, https://github.com/jsirois/dev-cmd/blob/main/CHANGES.md
Keywords: automation,command,runner,testing
Classifier: Development Status :: 4 - Beta
Classifier: Environment :: Console
Classifier: Intended Audience :: Developers
Classifier: Operating System :: MacOS :: MacOS X
Classifier: Operating System :: Microsoft :: Windows
Classifier: Operating System :: POSIX :: Linux
Classifier: Operating System :: Unix
Classifier: Programming Language :: Python
Classifier: Programming Language :: Python :: 3 :: Only
Classifier: Programming Language :: Python :: 3.9
Classifier: Programming Language :: Python :: 3.10
Classifier: Programming Language :: Python :: 3.11
Classifier: Programming Language :: Python :: 3.12
Classifier: Programming Language :: Python :: 3.13
Classifier: Programming Language :: Python :: 3.14
Classifier: Topic :: Software Development :: Build Tools
Classifier: Topic :: Utilities
Requires-Python: >=3.9
License-File: LICENSE
Requires-Dist: aioconsole
Requires-Dist: ansicolors
Requires-Dist: colorama; sys_platform == "win32"
Requires-Dist: packaging
Requires-Dist: tomli; python_version < "3.11"
Requires-Dist: typing-extensions
Provides-Extra: old-pythons
Requires-Dist: pex; extra == "old-pythons"
Requires-Dist: filelock; extra == "old-pythons"
Dynamic: license-file
